pyairstage/__init__.py
pyairstage/airstageAC.py
pyairstage/airstageApi.py
pyairstage/constants.py
pyairstage-3.0.2.dist-info/licenses/LICENSE
pyairstage-3.0.2.dist-info/METADATA
pyairstage-3.0.2.dist-info/WHEEL
pyairstage-3.0.2.dist-info/top_level.txt
pyairstage-3.0.2.dist-info/RECORD
