Metadata-Version: 2.4
Name: pyairstage
Version: 3.0.2
Summary: Python library to control Fujitsu Airstage Airconditioners
Home-page: https://github.com/danielkaldheim/pyairstage
Author: Daniel Rufus Kaldheim
Author-email: daniel@kaldheim.org
License: MIT
Classifier: Programming Language :: Python :: 3
Classifier: Operating System :: OS Independent
License-File: LICENSE
Requires-Dist: aiohttp
Dynamic: author
Dynamic: author-email
Dynamic: classifier
Dynamic: description
Dynamic: description-content-type
Dynamic: home-page
Dynamic: license
Dynamic: license-file
Dynamic: requires-dist
Dynamic: summary
